{
  "version": 1,
  "exerciseType": "dragging",
  "items": [
    {
      "id": "ee7ca9e1-c760-4609-9ec8-d4414759defb",
      "text": "I [went] to the store yesterday and [bought] some groceries."
    },
    {
      "id": "56ed091d-1051-4269-849b-2edcc177a3f2",
      "text": "She [is] very happy today because she [finished] her project."
    },
    {
      "id": "dfb34029-e75a-40d8-9e84-76b0ad6a335c",
      "text": "They are [buying] a new house and [are] planning to move next month."
    }
  ],
  "fakeOptions": [],
  "secretKey": "6b21146743b6a7f039e5c36c27625d8af8522fbfa4c026d8d260da93d79ec09a"
}
